techsummarizer/__init__.py
techsummarizer/main.py
techsummarizer/prompts.py
techsummarizer-2025.12.21141722.dist-info/METADATA
techsummarizer-2025.12.21141722.dist-info/WHEEL
techsummarizer-2025.12.21141722.dist-info/top_level.txt
techsummarizer-2025.12.21141722.dist-info/RECORD
