Metadata-Version: 2.4
Name: techsummarizer
Version: 2025.12.21141722
Summary: A new package is designed to analyze and summarize technical articles or announcements by extracting structured key information from user-provided text. It leverages language models to identify and or
Author-email: techsummarizer <hi@eugene.plus>
License: MIT
Project-URL: Homepage, https://github.com/chigwell/techsummarizer
Requires-Python: >=3.9
Requires-Dist: langchain-llm7>=0.0.0
Requires-Dist: llmatch-messages>=0.0.0
Requires-Dist: langchain-core>=0.3.0
